odoo9_addon_server_environment_files_sample-9.0.1.0.0-py2.7-nspkg.pth
odoo9_addon_server_environment_files_sample-9.0.1.0.0.dist-info/top_level.txt
odoo9_addon_server_environment_files_sample-9.0.1.0.0.dist-info/WHEEL
odoo9_addon_server_environment_files_sample-9.0.1.0.0.dist-info/RECORD
odoo9_addon_server_environment_files_sample-9.0.1.0.0.dist-info/metadata.json
odoo9_addon_server_environment_files_sample-9.0.1.0.0.dist-info/DESCRIPTION.rst
odoo9_addon_server_environment_files_sample-9.0.1.0.0.dist-info/METADATA
odoo9_addon_server_environment_files_sample-9.0.1.0.0.dist-info/namespace_packages.txt
odoo_addons/server_environment_files_sample/__openerp__.py
odoo_addons/server_environment_files_sample/__init__.py
odoo_addons/server_environment_files_sample/README.rst
odoo_addons/server_environment_files_sample/dev/base.conf
odoo_addons/server_environment_files_sample/dev/mytopic.conf
odoo_addons/server_environment_files_sample/default/base.conf
odoo_addons/server_environment_files_sample/default/mytopic.conf
odoo_addons/server_environment_files_sample/prod/base.conf
odoo_addons/server_environment_files_sample/prod/mytopic.conf
odoo_addons/server_environment_files_sample/i18n/server_environment_files.pot
odoo_addons/server_environment_files_sample/preprod/mytopic.conf
odoo_addons/server_environment_files_sample/static/description/icon.png
