Metadata-Version: 2.0
Name: odoo9-addon-server-environment-files-sample
Version: 9.0.1.0.0
Summary: sample config file for server_environment
Home-page: http://www.camptocamp.com
Author: UNKNOWN
Author-email: UNKNOWN
License: GPL-3 or any later version
Platform: UNKNOWN
Requires-Dist: odoo (<9.1a,>=9.0a)
Classifier: Programming Language :: Python :: 2.7
Classifier: Framework :: Odoo
Classifier: License :: OSI Approved :: GNU General Public License v3 or later (GPLv3+)
